{
    "photo":[
        {
            "src":"img/img_strg_01.jpg",
            "title":"현대 모터스튜디오 고양",
            "exp":"국내 최대의 체험형 자동차 테마파크로 자동차의 탄생 과정과 기능을 친근하고 즐겁게 체험할 수 있는 공간입니다."
        },
        {
            "src":"img/img_strg_02.jpg",
            "title":"현대 모터스튜디오 서울",
            "exp":"현대자동차의 새로운 실험실인 이곳, 자동차가 건네는 노라운 이야기에 귀 기울여 보세요."
        },
        {
            "src":"img/img_strg_03.jpg",
            "title":"현대 모터스튜디오 하남",
            "exp":"무한 가능성과 혁신적 시도가 가득한 이 곳에서 미래의 라이프스타일을 경험하실 수 있습니다."
        },
        {
            "src":"img/img_strg_busan.jpg",
            "title":"현대 모터스튜디오 부산",
            "exp":"Design to live by<br>평범한 일상을 풍요롭게 하는 디자인 체험공간"
        },
        {
            "src":"img/img_strg_04.jpg",
            "title":"현대 모터스튜디오 베이징",
            "exp":"창의적인 생각과 예술을 통해 고객과 소통합니다."
        }
    ]
}